lanutils/__init__.py
lanutils/lanutils.py
lanutils-1.0.0.dist-info/METADATA
lanutils-1.0.0.dist-info/WHEEL
lanutils-1.0.0.dist-info/entry_points.txt
lanutils-1.0.0.dist-info/licenses/LICENSE.txt
lanutils-1.0.0.dist-info/RECORD
