Metadata-Version: 2.1
Name: lanutils
Version: 1.0.0
Summary: Small package to probe ip addresses and ports on a local network
Project-URL: Homepage, https://github.com/matt-manes/lanutils
Project-URL: Documentation, https://github.com/matt-manes/lanutils/tree/main/docs
Project-URL: Source code, https://github.com/matt-manes/lanutils/tree/main/src/lanutils
Author-email: Matt Manes <mattmanes@pm.me>
License-File: LICENSE.txt
Keywords: discovery,lan,network,networking
Classifier: License :: OSI Approved :: MIT License
Classifier: Operating System :: OS Independent
Classifier: Programming Language :: Python :: 3
Requires-Python: >=3.6
Requires-Dist: icmplib
Requires-Dist: ifaddr
